summer/__init__.py
summer/anno/__init__.py
summer/anno/annos.py
summer/cacode/Factory.py
summer/cacode/Modes.py
summer/cacode/Serialize.py
summer/cacode/__init__.py
summer/cacode/ReviewJson/JSON.py
summer/cacode/ReviewJson/__init__.py
summer/cacode/ReviewJson/compat.py
summer/cacode/ReviewJson/decoder.py
summer/cacode/ReviewJson/encoder.py
summer/cacode/ReviewJson/errors.py
summer/cacode/ReviewJson/ordered_dict.py
summer/cacode/ReviewJson/raw_json.py
summer/cacode/ReviewJson/scanner.py
summer/cacode/ReviewJson/tool.py
summer/exception/__init__.py
summer/exception/e_fields.py
summer/field/FManage.py
summer/field/MySqlDefault.py
summer/field/__init__.py
summer/field/tag.py
summer/opera/__init__.py
summer/opera/global_db.py
summer/opera/op_db.py
summer/opera/DBPool/__init__.py
summer/opera/DBPool/persistent_db.py
summer/opera/DBPool/persistent_pg.py
summer/opera/DBPool/pooled_db.py
summer/opera/DBPool/pooled_pg.py
summer/opera/DBPool/simple_pooled_db.py
summer/opera/DBPool/simple_pooled_pg.py
summer/opera/DBPool/steady_db.py
summer/opera/DBPool/steady_pg.py
summer/util/CompulsoryRun.py
summer/util/Log.py
summer/util/ParseUtil.py
summer/util/__init__.py
summer/work/AopContainer.py
summer/work/Config.py
summer/work/Manage.py
summer/work/SummerAdapter.py
summer/work/__init__.py
summer/work/orm.py
summer/work/repository.py
test/__init__.py
test/testFunc.py
test/modules/DatabaseConf.py
test/modules/MySqlTest.py
test/modules/SqlServerTest.py
test/modules/__init__.py
test/t_thread_pool/__init__.py
summer_python-1.0.0b2.dist-info/LICENSE
summer_python-1.0.0b2.dist-info/METADATA
summer_python-1.0.0b2.dist-info/WHEEL
summer_python-1.0.0b2.dist-info/top_level.txt
summer_python-1.0.0b2.dist-info/RECORD
