Metadata-Version: 2.1
Name: summer-python
Version: 1.0.0b2
Summary: Summer framework for Python,You can see:https://gitee.com/cacode_cctvadmin/summer-python
Home-page: https://gitee.com/cacode_cctvadmin/summer-python
Author: CACode
Author-email: cacode@163.com
License: Apache License 2.0
Project-URL: Bug Tracker, https://gitee.com/cacode_cctvadmin/summer-python/issues
Platform: UNKNOWN
Classifier: Programming Language :: Python :: 3
Classifier: License :: OSI Approved :: MIT License
Classifier: Operating System :: OS Independent
Requires-Python: >=3.6
